{
  "m_GameObject": {
    "m_FileID": 0,
    "m_PathID": -5374810038133428360
  },
  "m_Enabled": 1,
  "m_Script": {
    "m_FileID": 0,
    "m_PathID": 9018576197364432263
  },
  "m_Name": "",
  "iceFloorPrefab": {
    "m_FileID": 0,
    "m_PathID": -9014692679771835294
  },
  "hasAisleMargin": 0,
  "aisleWidth": 5,
  "bossRoomCoverage": 0.5,
  "aisleIceCoverage": 1.0,
  "fullIceRate": 0.1,
  "onInstantiateIceFloorEvent": {
    "m_PersistentCalls": {
      "m_Calls": [
        {
          "m_Target": {
            "m_FileID": 0,
            "m_PathID": 2777829367202477673
          },
          "m_MethodName": "AssignToIceFloorReflection",
          "m_Mode": 0,
          "m_Arguments": {
            "m_ObjectArgument": {
              "m_FileID": 0,
              "m_PathID": 0
            },
            "m_ObjectArgumentAssemblyTypeName": "UnityEngine.Object, UnityEngine",
            "m_IntArgument": 0,
            "m_FloatArgument": 0.0,
            "m_StringArgument": "",
            "m_BoolArgument": 0
          },
          "m_CallState": 2
        }
      ]
    }
  },
  "onInstantiateAisleIceFloorEvent": {
    "m_PersistentCalls": {
      "m_Calls": [
        {
          "m_Target": {
            "m_FileID": 0,
            "m_PathID": -6289130333553595686
          },
          "m_MethodName": "OnInstantiateIceFloor",
          "m_Mode": 0,
          "m_Arguments": {
            "m_ObjectArgument": {
              "m_FileID": 0,
              "m_PathID": 0
            },
            "m_ObjectArgumentAssemblyTypeName": "UnityEngine.Object, UnityEngine",
            "m_IntArgument": 0,
            "m_FloatArgument": 0.0,
            "m_StringArgument": "",
            "m_BoolArgument": 0
          },
          "m_CallState": 2
        }
      ]
    }
  },
  "exclusiveRoomTypes": [
    3
  ],
  "canGenerateIndex": 0
}