{
  "m_GameObject": {
    "m_FileID": 0,
    "m_PathID": 7316962138092796916
  },
  "m_Enabled": 1,
  "m_Script": {
    "m_FileID": 0,
    "m_PathID": -6104616099792334479
  },
  "m_Name": "",
  "serializationData": {
    "SerializedFormat": 0,
    "SerializedBytes": [],
    "ReferencedUnityObjects": [],
    "SerializedBytesString": "",
    "Prefab": {
      "m_FileID": 0,
      "m_PathID": 0
    },
    "PrefabModificationsReferencedUnityObjects": [],
    "PrefabModifications": [],
    "SerializationNodes": []
  },
  "item_name": "object/robot",
  "item_value": 0,
  "repeat": 0,
  "statisticKey": ""
}